bxmsdk/__init__.py
bxmsdk/doe2/__init__.py
bxmsdk/energyplus/__init__.py
bxmsdk/energyplus/epTranslator.py
bxmsdk/energyplus/simEngine/__init__.py
bxmsdk-0.12.0.dist-info/LICENSE.txt
bxmsdk-0.12.0.dist-info/METADATA
bxmsdk-0.12.0.dist-info/WHEEL
bxmsdk-0.12.0.dist-info/top_level.txt
bxmsdk-0.12.0.dist-info/RECORD
