Metadata-Version: 2.1
Name: bxmsdk
Version: 0.12.0
Summary: software development kit to develope models for building simulation
Home-page: UNKNOWN
Author: Sagar Rao
Author-email: sagarurao@gmail.com
License: GNU GPL 3
Platform: UNKNOWN
